sphinx_image_inverter/__init__.py
sphinx_image_inverter/_version.py
sphinx_image_inverter/static/image_dark_mode.css
sphinx_image_inverter/static/image_dark_mode_alt.css
sphinx_image_inverter-1.1.11.dist-info/METADATA
sphinx_image_inverter-1.1.11.dist-info/WHEEL
sphinx_image_inverter-1.1.11.dist-info/licenses/LICENSE
sphinx_image_inverter-1.1.11.dist-info/RECORD
