Metadata-Version: 2.4
Name: sphinx-image-inverter
Version: 1.1.11
Summary: Custom CSS that inverts the colors of images when a dark theme is toggled.
Author-email: Caspar Jungbacker <c.a.a.jungbacker@tudelft.nl>, Rok Štular <rstular@student.tudelft.nl>
License-File: LICENSE
Requires-Python: >=3.10
Requires-Dist: sphinx
